astabc/__init__.py
astabc/astabc.py
astabc-0.1.12.dist-info/LICENSE
astabc-0.1.12.dist-info/METADATA
astabc-0.1.12.dist-info/WHEEL
astabc-0.1.12.dist-info/entry_points.txt
astabc-0.1.12.dist-info/top_level.txt
astabc-0.1.12.dist-info/RECORD
