Metadata-Version: 2.1
Name: astabc
Version: 0.1.12
Summary: A Python module for automatic brightness and contrast optimization
Home-page: https://github.com/jgwill/gia-abc
Author: Guillaume Descoteaux-Isabelle
Classifier: Programming Language :: Python :: 3
Classifier: License :: OSI Approved :: MIT License
Classifier: Operating System :: OS Independent
License-File: LICENSE
Requires-Dist: opencv-python
